suture_run/__init__.py
suture_run-0.1.3.dist-info/METADATA
suture_run-0.1.3.dist-info/WHEEL
suture_run-0.1.3.dist-info/entry_points.txt
suture_run-0.1.3.dist-info/top_level.txt
suture_run-0.1.3.dist-info/RECORD
