Metadata-Version: 2.4
Name: suture-run
Version: 0.1.3
Summary: Prompt Surgery
Requires-Python: >=3.10
